{
  "experiment_info": {
    "timestamp": "2025-07-03 16:27:03",
    "dataset": "Texas",
    "model": "H2GCN"
  },
  "total_experiments": 90,
  "final_results": {
    "train": {
      "mean": 1.0,
      "std": 0.0
    },
    "val": {
      "mean": 0.8401234567901235,
      "std": 0.05419809330679219
    },
    "test": {
      "mean": 0.8611111111111109,
      "std": 0.06026868354576919
    }
  },
  "best_results": {
    "val": {
      "mean": 0.8808641975308643,
      "std": 0.046893270457552316
    },
    "test": {
      "mean": 0.8383040935672514,
      "std": 0.059824447073913364
    }
  },
  "early_stopping": {
    "early_stopped_experiments": 90,
    "early_stopping_rate": 1.0,
    "average_stopping_epoch": 75.73333333333333,
    "stopping_epoch_std": 22.907931668601886,
    "stopping_epoch_range": [
      52,
      194
    ]
  }
}